Workbook

Sheet OGDCL
A1: Oil & Gas Development Company Limited (OGDCL)
A3: Full Name: Oil & Gas Development Company Limited | B3: About OGDCL
A4: PSX Ticker: OGDC | B4: OGDCL is Pakistan's largest exploration and production (E&P) company and a key pillar of the country's energy security. Established in 1961 as a government-owned corporation and subsequently converted into a public limited company in 1997, OGDCL operates one of the most diversified upstream portfolios in Pakistan.
A5: Industry: Upstream Oil & Gas Exploration & Production | B5: The company holds working interests in 52 exploration licences and development & production leases across Pakistan, making it the single largest contributor to the country's domestic oil and gas production. OGDCL's production base includes crude oil, natural gas, LPG, and sulphur.
A6: Founded: 1961 (incorporated as a company in 1997) | B6: Beyond E&P, OGDCL holds strategic equity stakes in associated companies including Pakistan Petroleum Limited (PPL), Pakistan LNG Limited, and others, which contribute substantial dividend income and share of profit, recorded under 'other income' in the income statement.
A7: Headquarters: Islamabad, Pakistan
A8: Ownership: Government of Pakistan (~69% stake)
A9: Shares Outstanding: 4,300.93 million
A10: Market Cap (FY2024): ~PKR 581,162 mn at PKR 135.15/share
A11: Fiscal Year End: 30 June
A12: Listing: Pakistan Stock Exchange (PSX)

Sheet DCF_INPUT_CALCS
A1: OGDC – DCF Input Calculations (FY2022–FY2024)
A3: A) Source figures from Annual Report PDFs (units: Rupees ‘000)
A4: Year | B4: PBT | C4: Tax | D4: Effective tax rate | E4: Cash & bank | F4: Other financial assets | G4: Current portion of LT investments | H4: Interest-bearing debt | I4: Net debt (cash only) PKR mn | J4: Net debt (cash+otherFA) PKR mn | K4: Net debt (cash+otherFA+CPLTI) PKR mn | L4: Shares outstanding (mn)
A5: 2022 | B5: 232521360 | C5: 98737613 | D5: 0.42463889 | E5: 31631051 | F5: 48539965 | G5: 140694637 | H5: 0 | I5: -31631.051 | J5: -80171.016 | K5: -220865.65 | L5: 4300.9284
A6: 2023 | B6: 383772763 | C6: 159154966 | D6: 0.41471147 | E6: 25765707 | F6: 87304487 | G6: 155694636 | H6: 0 | I6: -25765.707 | J6: -113070.19 | K6: -268764.83 | L6: 4300.9284
A7: 2024 | B7: 293787094 | C7: 84811323 | D7: 0.28868294 | E7: 141030201 | F7: 117970327 | G7: 17091021 | H7: 0 | I7: -141030.2 | J7: -259000.53 | K7: -276091.55 | L7: 4300.9284
A9: B) Recommended single inputs for the DCF
A10: Input | B10: Recommended value | C10: Why this value (rule) | E10: =C5/B5*100 -> 42.463889 | F10: =SUM(E10:E12)/3 -> 37.60111
A11: Tax rate | B11: 0.37656409 | C11: 3-year weighted effective tax rate = ΣTax/ΣPBT (smooths one-off tax spikes). | E11: =C6/B6*100 -> 41.471147 | H11: `
A12: WACC | B12: 0.264758 | C12: With ~0 debt, WACC≈Cost of equity. Re = Rf + β×ERP. (Inputs documented below). | E12: =C7/B7*100 -> 28.868294
A13: Terminal growth (g) | B13: 0.04 | C13: Conservative long-run growth; keep below WACC (g < WACC). | D13: This is an assumption
A14: Shares outstanding (mn) | B14: 4300.9284 | C14: From share capital and face value; constant across FY22–FY24.
A15: Net debt (PKR mn) | B15: -259000.53 | C15: Use latest year (valuation date). Selected definition: Debt − (Cash & bank + Other financial assets). | D15: Find “Debt” In liabilities section, we have: deferred taxation deferred employee benefits provision for decommissioning cost trade & other payables unpaid dividend These are NOT interest-bearing debt. Interest-bearing debt would look like: Borrowings / Loans / Bank debt / Sukuk / Bonds / Lease liabilities Since the face of the statement shows no borrowings, we treat: Debt≈0
A18: Parameter | B18: Value | C18: Meaning / Source
A19: Risk-free rate (Rf) | B19: 0.1156 | C19: Pakistan 10-year government bond yield (as of Feb 27, 2026)
A20: Beta (β) | B20: 1.07 | C20: OGDC beta (TradingView) | D20: β=Cov(Rstock​,Rmarket​)/Var(Rmarket​)
A21: Equity risk premium (ERP) | B21: 0.1394 | C21: Pakistan total equity risk premium (Damodaran; Jan 2026) https://pages.stern.nyu.edu/~adamodar/New_Home_Page/datafile/ctryprem.html
A22: Cost of equity Re | B22: 0.264758 | C22: Re = Rf + β×ERP

Sheet INPUTS
A1: Model Inputs
A3: General
A4: Item | B4: Value | C4: FY2022 Share Price | D4: FY2023 Share Price | E4: FY2024 Share Price
A5: Company name | B5: OGDCL | C5: 78.9 | D5: 77.85 | E5: 135.15
A6: Peer Company | B6: POL | C6: 405.81 | D6: 401.77 | E6: 489.94
A7: Currency / units | B7: PKR mn
A8: Historical years | B8: FY2022–FY2024
A9: Valuation assumptions (DCF)
A10: Item | B10: Value | C10: Notes
A11: Tax rate | B11: 0.37656409 | C11: 3-year weighted effective tax rate (FY2022–FY2024) = ΣTax/ΣPBT
A12: WACC | B12: 0.264758 | C12: WACC≈Cost of Equity (no interest-bearing debt); Re=Rf+β*ERP (Rf=11.56%, β=1.07, ERP=13.94%)
A13: Terminal growth (g) | B13: 0.04 | C13: Terminal growth assumption (conservative)
A14: Shares outstanding (mn) | B14: 4300.9284 | C14: From share capital / face value (Rs '000): 43,009,284 / 10 = 4,300,928.4 ('000) => 4,300.93 mn
A15: Net debt (PKR mn) | B15: -259000.53 | C15: Net debt = Debt − (Cash & bank + Other financial assets) (FY2024). Alternative definitions in DCF_INPUT_CALCS.

Sheet INCOME_S
A1: Income Statement (PKR mn)
A3: Line item | B3: FY2022 | C3: FY2023 | D3: FY2024 | E3: Growth23​ | F3: Growth24​
A4: Revenue | B4: =335463725/1000 -> 335463.72 | C4: =413594009/1000 -> 413594.01 | D4: =463697861/1000 -> 463697.86 | E4: =(C4/B4)-1 -> 0.23290233 | F4: =(D4/C4)-1 -> 0.1211426
A5: Cost of sales | B5: =118548101/1000 -> 118548.1 | C5: =143867373/1000 -> 143867.37 | D5: =180384890/1000 -> 180384.89 | F5: =(D5/C5)-1 -> 0.25382765
A6: Gross profit | B6: =B4-B5 -> 216915.62 | C6: =C4-C5 -> 269726.64 | D6: =D4-D5 -> 283312.97 | F6: =(D6/C6)-1 -> 0.050370758
A7: Operating expenses | B7: =32734212/1000 -> 32734.212 | C7: =46474060/1000 -> 46474.06 | D7: =36912918/1000 -> 36912.918 | F7: =(D7/C7)-1 -> -0.20573072
A8: EBIT | B8: =B6-B7+(46570522/1000)+(4109622/1000) -> 234861.56 | C8: =C6-C7+(154692085/1000)+(10543257/1000) -> 388487.92 | D8: =D6-D7+(41343692/1000)+(13186479/1000) -> 300930.22 | F8: =(D8/C8)-1 -> -0.22538074
A9: Net finance cost | B9: =2340196/1000 -> 2340.196 | C9: =4715155/1000 -> 4715.155 | D9: =7143130/1000 -> 7143.13 | F9: =(D9/C9)-1 -> 0.51493005
A10: Profit before tax | B10: =B8-B9 -> 232521.36 | C10: =C8-C9 -> 383772.76 | D10: =D8-D9 -> 293787.09 | F10: =(D10/C10)-1 -> -0.23447643
A11: Tax | B11: =98737613/1000 -> 98737.613 | C11: =159154966/1000 -> 159154.97 | D11: =84811323/1000 -> 84811.323 | F11: =(D11/C11)-1 -> -0.46711482
A12: Net profit | B12: =B10-B11 -> 133783.75 | C12: =C10-C11 -> 224617.8 | D12: =D10-D11 -> 208975.77 | F12: =(D12/C12)-1 -> -0.069638409

Sheet BALANCE_S
A1: Balance Sheet (PKR mn)
A3: Line item | B3: FY2022 | C3: FY2023 | D3: FY2024
A4: Cash & equivalents | B4: 31631.051 | C4: 25765.707 | D4: 141030.2
A5: Accounts receivable | B5: 456594.83 | C5: 576968.55 | D5: 635016.33
A6: Inventory | B6: 20518.894 | C6: 23398.716 | D6: 24438.953
A7: Other current assets | B7: 269792.85 | C7: 332984.67 | D7: 260003.75
A8: Total current assets | B8: =SUM( B4:B7) -> 778537.63 | C8: =SUM(C4:C7) -> 959117.64 | D8: =SUM(D4:D7) -> 1060489.2
A9: PPE / fixed assets | B9: 224208.56 | C9: 214519.24 | D9: 226572.58
A10: Other non-current assets | B10: 127236.87 | C10: 250428.42 | D10: 317192.33
A11: Total assets | B11: =SUM(B8:B10) -> 1129983.1 | C11: =SUM(C8:C10) -> 1424065.3 | D11: =SUM(D8:D10) -> 1604254.1
A12: Accounts payable | B12: 105121.44 | C12: 123306.18 | D12: 139527.26
A13: Short-term debt | B13: 0 | C13: 0 | D13: 0
A14: Other current liabilities | B14: 33944.084 | C14: 37657.827 | D14: 41328.84
A15: Total current liabilities | B15: =SUM( B12:B14) -> 139065.52 | C15: =SUM(C12:C14) -> 160964.01 | D15: =SUM(D12:D14) -> 180856.1
A16: Long-term debt | B16: 0 | C16: 0 | D16: 0
A17: Other non-current liabilities | B17: 115524.96 | C17: 180203.41 | D17: 172901.82
A18: Total liabilities | B18: =SUM( B15:B17) -> 254590.49 | C18: =SUM(C15:C17) -> 341167.42 | D18: =SUM(D15:D17) -> 353757.92
A19: Share capital | B19: 43009.284 | C19: 43009.284 | D19: 43009.284
A20: Retained earnings | B20: 832383.28 | C20: 1039888.6 | D20: 1207486.9
A21: Total equity | B21: =B19+B20 -> 875392.57 | C21: =C19+C20 -> 1082897.9 | D21: =D19+D20 -> 1250496.2
A22: Total liabilities & equity | B22: =B18+B21 -> 1129983.1 | C22: =C18+C21 -> 1424065.3 | D22: =D18+D21 -> 1604254.1
A24: NWC | B24: =(B5+B6+B7)-(B12+B14) -> 607841.05 | C24: =(C5+C6+C7)-(C12+C14) -> 772387.92 | D24: =(D5+D6+D7)-(D12+D14) -> 738602.93
A25: ΔNWC | C25: =C24-B24 -> 164546.87 | D25: =D24-C24 -> -33784.989
A26: ΔNWC% | C26: =C25/INCOME_S!C4 -> 0.39784636 | D26: =D25/INCOME_S!D4 -> -0.07285992
A27: NWC= | B27: (AR+Inventory+other CA)-(AP+ other CL)

Sheet CF_S
A1: Cash Flow Statement (PKR mn)
A3: Line item | B3: FY2022 | C3: FY2023 | D3: FY2024
A4: Cash flow from operations (CFO) | B4: 72364.346 | C4: 27817.162 | D4: 104763.92
A5: Cash flow from investing (CFI) | B5: -49752.91 | C5: 12234.661 | D5: 78939.919
A6: Cash flow from financing (CFF) | B6: -22258.867 | C6: -31983.963 | D6: -34392.203
A7: Net change in cash | B7: =SUM(B4:B6) -> 352.569 | C7: =SUM(C4:C6) -> 8067.86 | D7: =SUM(D4:D6) -> 149311.64
A8: FX impact on cash (from cash flow statement) | B8: 16063.029 | C8: 79875.942 | D8: -3538.759
A9: Opening cash balance | B9: 63460.344 | C9: 24896.562 | D9: 112840.36
A10: Closing cash balance (check vs BS) | B10: =SUM(B7:B9) -> 79875.942 | C10: =SUM(C7:C9) -> 112840.36 | D10: =SUM(D7:D9) -> 258613.24
A12: CAPEX | B12: -25130 | C12: -13180.8 | D12: -45036.4
A13: CAPEX % Of Revenue | B13: =-B12/INCOME_S!B4 -> 0.074911229 | C13: =-C12/INCOME_S!C4 -> 0.031868934 | D13: =-D12/INCOME_S!D4 -> 0.097124451

Sheet COMMON_SIZE
A1: Common-Size & Trend (It converts financial statements into percentages so we can compare performance across years (and against peers) even when the company’s size changes)
A3: Income statement as % of Revenue
A4: Line item | B4: FY2022 | C4: FY2023 | D4: FY2024
A5: Revenue | B5: =INCOME_S!B4/INCOME_S!B4 -> 1 | C5: =INCOME_S!C4/INCOME_S!C4 -> 1 | D5: =INCOME_S!D4/INCOME_S!D4 -> 1
A6: Cost of sales | B6: =INCOME_S!B5/INCOME_S!B4 -> 0.35338575 | C6: =INCOME_S!C5/INCOME_S!C4 -> 0.34784685 | D6: =INCOME_S!D5/INCOME_S!D4 -> 0.38901385
A7: Gross profit | B7: =(INCOME_S!B6/INCOME_S!B4) -> 0.64661425 | C7: =(INCOME_S!C6/INCOME_S!C4) -> 0.65215315 | D7: =(INCOME_S!D6/INCOME_S!D4) -> 0.61098615
A8: Operating expenses | B8: =(INCOME_S!B7/INCOME_S!B4) -> 0.097578992 | C8: =(INCOME_S!C7/INCOME_S!C4) -> 0.11236638 | D8: =(INCOME_S!D7/INCOME_S!D4) -> 0.079605539
A9: EBIT | B9: =(INCOME_S!B8/INCOME_S!B4) -> 0.70011014 | C9: =(INCOME_S!C8/INCOME_S!C4) -> 0.93929774 | D9: =(INCOME_S!D8/INCOME_S!D4) -> 0.64897911
A10: Net finance cost | B10: =(INCOME_S!B9/INCOME_S!B4) -> 0.0069760031 | C10: =(INCOME_S!C9/INCOME_S!C4) -> 0.011400443 | D10: =(INCOME_S!D9/INCOME_S!D4) -> 0.015404708
A11: Profit before tax | B11: =(INCOME_S!B10/INCOME_S!B4) -> 0.69313414 | C11: =(INCOME_S!C10/INCOME_S!C4) -> 0.9278973 | D11: =(INCOME_S!D10/INCOME_S!D4) -> 0.6335744
A12: Tax | B12: =(INCOME_S!B11/INCOME_S!B4) -> 0.29433171 | C12: =(INCOME_S!C11/INCOME_S!C4) -> 0.38480965 | D12: =(INCOME_S!D11/INCOME_S!D4) -> 0.18290212
A13: Net profit | B13: =(INCOME_S!B12/INCOME_S!B4) -> 0.39880242 | C13: =(INCOME_S!C12/INCOME_S!C4) -> 0.54308765 | D13: =(INCOME_S!D12/INCOME_S!D4) -> 0.45067228
A16: Balance sheet as % of Total Assets
A17: Line item | B17: FY2022 | C17: FY2023 | D17: FY2024
A18: Cash & equivalents | B18: =(BALANCE_S!B4/BALANCE_S!B11) -> 0.0279925 | C18: =(BALANCE_S!C4/BALANCE_S!C11) -> 0.018093066 | D18: =(BALANCE_S!D4/BALANCE_S!D11) -> 0.087910137
A19: Accounts receivable | B19: =(BALANCE_S!B5/BALANCE_S!B11) -> 0.40407228 | C19: =(BALANCE_S!C5/BALANCE_S!C11) -> 0.40515596 | D19: =(BALANCE_S!D5/BALANCE_S!D11) -> 0.39583275
A20: Inventory | B20: =(BALANCE_S!B6/BALANCE_S!B11) -> 0.018158586 | C20: =(BALANCE_S!C6/BALANCE_S!C11) -> 0.016430929 | D20: =(BALANCE_S!D6/BALANCE_S!D11) -> 0.015233841
A21: Total current assets | B21: =(BALANCE_S!B8/BALANCE_S!B11) -> 0.68898168 | C21: =(BALANCE_S!C8/BALANCE_S!C11) -> 0.67350678 | D21: =(BALANCE_S!D8/BALANCE_S!D11) -> 0.66104815
A22: PPE / fixed assets | B22: =(BALANCE_S!B9/BALANCE_S!B11) -> 0.19841763 | C22: =(BALANCE_S!C9/BALANCE_S!C11) -> 0.15063862 | D22: =(BALANCE_S!D9/BALANCE_S!D11) -> 0.14123235
A23: Total assets | B23: =(BALANCE_S!B11/BALANCE_S!B11) -> 1 | C23: =(BALANCE_S!C11/BALANCE_S!C11) -> 1 | D23: =(BALANCE_S!D11/BALANCE_S!D11) -> 1
A24: Total liabilities | B24: =(BALANCE_S!B18/BALANCE_S!B11) -> 0.22530469 | C24: =(BALANCE_S!C18/BALANCE_S!C11) -> 0.23957288 | D24: =(BALANCE_S!D18/BALANCE_S!D11) -> 0.22051239
A25: Total equity | B25: =(BALANCE_S!B21/BALANCE_S!B11) -> 0.77469531 | C25: =(BALANCE_S!C21/BALANCE_S!C11) -> 0.76042712 | D25: =(BALANCE_S!D21/BALANCE_S!D11) -> 0.77948761

Sheet RATIOS
A1: Key Ratios
A3: Ratio | B3: FY2022 | C3: FY2023 | D3: FY2024 | E3: Formulas | F3: Interpretation
A4: Gross margin | B4: =(INCOME_S!B6/INCOME_S!B4) -> 0.64661425 | C4: =(INCOME_S!C6/INCOME_S!C4) -> 0.65215315 | D4: =(INCOME_S!D6/INCOME_S!D4) -> 0.61098615 | E4: Gross Profit/Revenue | F4: Pricing power / cost control
A5: EBIT margin | B5: =(INCOME_S!B8/INCOME_S!B4) -> 0.70011014 | C5: =(INCOME_S!C8/INCOME_S!C4) -> 0.93929774 | D5: =(INCOME_S!D8/INCOME_S!D4) -> 0.64897911 | E5: EBIT/Revenue | F5: Operating efficiency
A6: Net margin | B6: =(INCOME_S!B12/INCOME_S!B4) -> 0.39880242 | C6: =(INCOME_S!C12/INCOME_S!C4) -> 0.54308765 | D6: =(INCOME_S!D12/INCOME_S!D4) -> 0.45067228 | E6: Net Profit/Revenue | F6: Bottom-line profitability
A7: ROA | B7: =(INCOME_S!B12/BALANCE_S!B11) -> 0.11839447 | C7: =(INCOME_S!C12/BALANCE_S!C11) -> 0.15772998 | D7: =(INCOME_S!D12/BALANCE_S!D11) -> 0.13026351 | E7: Net Profit/Total Assets | F7: Profit per asset; capital intensity
A8: ROE | B8: =(INCOME_S!B12/BALANCE_S!B21) -> 0.15282715 | C8: =(INCOME_S!C12/BALANCE_S!C21) -> 0.20742288 | D8: =(INCOME_S!D12/BALANCE_S!D21) -> 0.16711428 | E8: Net Profit/Total Equity | F8: Return to shareholders
A9: Current ratio | B9: =(BALANCE_S!B8/BALANCE_S!B15) -> 5.5983511 | C9: =(BALANCE_S!C8/BALANCE_S!C15) -> 5.9585845 | D9: =(BALANCE_S!D8/BALANCE_S!D15) -> 5.8637183 | E9: Current Assets/Current Liabilities | F9: Liquidity buffer
A10: Debt / Equity | B10: =(BALANCE_S!B18/BALANCE_S!B21) -> 0.29083008 | C10: =(BALANCE_S!C18/BALANCE_S!C21) -> 0.31505041 | D10: =(BALANCE_S!D18/BALANCE_S!D21) -> 0.28289404 | E10: Total Debt/Total Equity | F10: Leverage / solvency
A11: Interest coverage | B11: =INCOME_S!B8/ABS(INCOME_S!B9) -> 100.35978 | C11: =INCOME_S!C8/ABS(INCOME_S!C9) -> 82.391336 | D11: =INCOME_S!D8/ABS(INCOME_S!D9) -> 42.128622 | E11: EBIT/Interest Expense | F11: Ability to service finance cost
A12: Cash conversion (CFO / NI) | B12: =(CF_S!B4/INCOME_S!B12) -> 0.54090536 | C12: =(CF_S!C4/INCOME_S!C12) -> 0.1238422 | D12: =(CF_S!D4/INCOME_S!D12) -> 0.50132089 | E12: CFO/Net Profit | F12: Earnings quality
A13: EPS | B13: =INCOME_S!B12/INPUTS!B14 -> 31.105783 | C13: =INCOME_S!C12/INPUTS!B14 -> 52.225421 | D13: =INCOME_S!D12/INPUTS!B14 -> 48.588526 | E13: Net Profit/Outstanding Shares | F13: Earnings Per Share
A14: BVPS | B14: =BALANCE_S!B21/INPUTS!B14 -> 203.53572 | C14: =BALANCE_S!C21/INPUTS!B14 -> 251.78235 | D14: =BALANCE_S!D21/INPUTS!B14 -> 290.7503 | E14: Total Equity/Outstanding Shares | F14: Book Value per Share
A15: P/E | B15: =INPUTS!C5/B13 -> 2.5365058 | C15: =INPUTS!D5/C13 -> 1.4906534 | D15: =INPUTS!E5/D13 -> 2.7815209 | E15: Share Price/EPS | F15: High P/E = market expects growth / low risk Low P/E = cheaper / higher risk / low expected growth
A16: P/B | B16: =INPUTS!C5/B14 -> 0.38764694 | C16: =INPUTS!D5/C14 -> 0.30919562 | D16: =INPUTS!E5/D14 -> 0.46483185 | E16: Share Price/BVPS | F16: P/B > 1 = market values company above its book equity P/B < 1 = market discounts assets / concerns about profitability/quality

Sheet POL_PEER
A1: Pakistan Oilfields Limited (POL) – Peer Company
A5: Item | B5: FY2022 (Rs '000) | C5: FY2023 (Rs '000) | D5: FY2024 (Rs '000) | E5: Conversion | F5: FY2022 (PKR mn) | G5: FY2023 (PKR mn) | H5: FY2024 (PKR mn)
A6: Net sales | B6: 51944902 | C6: 60952282 | D6: 65290432 | E6: ÷ 1,000 | F6: =B6/1000 -> 51944.902 | G6: =C6/1000 -> 60952.282 | H6: =D6/1000 -> 65290.432
A7: Profit before tax (PBT) | B7: 36987380 | E7: ÷ 1,000 | F7: =B7/1000 -> 36987.38 | G7: =C7/1000 -> 0 | H7: =D7/1000 -> 0
A8: Profit before income tax & final taxes (PBT+levy basis) | C8: 49658659 | D8: 53239270 | E8: ÷ 1,000 | F8: =B8/1000 -> 0 | G8: =C8/1000 -> 49658.659 | H8: =D8/1000 -> 53239.27
A9: Finance costs - net (absolute) | B9: 5548542 | C9: 9619432 | D9: 3346894 | E9: ÷ 1,000 | F9: =B9/1000 -> 5548.542 | G9: =C9/1000 -> 9619.432 | H9: =D9/1000 -> 3346.894
A10: Profit for the year (Net profit) | B10: 25935113 | C10: 36452582 | D10: 39151511 | E10: ÷ 1,000 | F10: =B10/1000 -> 25935.113 | G10: =C10/1000 -> 36452.582 | H10: =D10/1000 -> 39151.511
A11: Total equity | B11: 51063461 | C11: 67687209 | D11: 82851974 | E11: ÷ 1,000 | F11: =B11/1000 -> 51063.461 | G11: =C11/1000 -> 67687.209 | H11: =D11/1000 -> 82851.974
A12: Total assets | B12: 118053932 | C12: 159038638 | D12: 175888636 | E12: ÷ 1,000 | F12: =B12/1000 -> 118053.93 | G12: =C12/1000 -> 159038.64 | H12: =D12/1000 -> 175888.64
A13: Total liabilities (assets - equity) | B13: 66990471 | C13: 91351429 | D13: 93036662 | E13: ÷ 1,000 | F13: =B13/1000 -> 66990.471 | G13: =C13/1000 -> 91351.429 | H13: =D13/1000 -> 93036.662
A14: EPS (Rupees) | C14: 128.42 | D14: 137.93
A15: FY2022 Share Price | B15: FY2023 Share Price | C15: FY2024 Share Price | D15: Outstanding Shares 2024
A16: 405.81 | B16: 401.77 | C16: 489.94 | D16: 283.855
A17: FY2024 Peer Metrics (used in PEER_COMP)
A18: Metric | B18: Formula | C18: Value (FY2024)
A19: Revenue (PKR mn) | C19: =H6 -> 65290.432
A20: EBIT margin | B20: EBIT / Net sales, where EBIT = PBT + finance costs | C20: =(H8+H9)/H6 -> 0.86668387
A21: ROE | B21: Net profit / Total Equity | C21: =H10/H11 -> 0.47254772
A22: Debt/Equity | B22: Total liabilities / Total equity | C22: =H13/H11 -> 1.1229263
A23: EPS | B23: Net Profit/Outstanding Shares | C23: =H10/C16 -> 79.910828
A24: P/E | B24: Share Price/EPS | C24: =C16/C23 -> 6.131084

Sheet PEER_COMP
A1: Peer Comparison
A3: Companies
A4: Primary company | B4: =INPUTS!B5 -> OGDCL
A5: Peer 1 | B5: POL
A6: Peer 2
A8: Key metrics (latest year 2024)
A9: Metric | B9: Company | C9: Peer 1 | D9: Peer 2
A10: Revenue (PKR mn) | B10: =INCOME_S!D4 -> 463697.86 | C10: 65290.432
A11: EBIT margin | B11: =RATIOS!D5 -> 0.64897911 | C11: =(POL_PEER!H8+POL_PEER!H9)/POL_PEER!H6 -> 0.86668387
A12: ROE | B12: =RATIOS!D8 -> 0.16711428 | C12: =POL_PEER!C21 -> 0.47254772
A13: Debt/Equity | B13: =RATIOS!D10 -> 0.28289404 | C13: =POL_PEER!C22 -> 1.1229263
A14: P/E | B14: =RATIOS!D15 -> 2.7815209 | C14: =POL_PEER!C24 -> 6.131084

Sheet FORECAST
A1: Forecast (3 years) — Simple Driver Based
A3: Revenue & margin Assumptions
A4: Assumption | B4: FY2025 | C4: FY2026 | D4: FY2027 | E4: Notes
A5: Revenue growth | B5: 0.05 | C5: 0.05 | D5: 0.05 | E5: used a conservative “steady-state” growth rate of 5% instead of repeating the last year’s growth (which can be volatile in oil & gas because prices/production swing).
A6: EBIT margin | B6: =RATIOS!D5 -> 0.64897911 | C6: =B6-1% -> 0.63897911 | D6: =C6-1% -> 0.62897911 | E6: Assuming operating profitability slowly declines by 1.0% per year
A7: Tax rate | B7: =INPUTS!B11 -> 0.37656409 | C7: =INPUTS!B11 -> 0.37656409 | D7: =INPUTS!B11 -> 0.37656409
A8: Capex (% of Revenue) | B8: =CF_S!D13 -> 0.097124451 | C8: =CF_S!D13 -> 0.097124451 | D8: =CF_S!D13 -> 0.097124451 | E8: Used Year 2024 As Base
A9: Change in NWC (% of Revenue) | B9: 0.01 | C9: 0.01 | D9: 0.01 | E9: Working capital has been volatile historically due to receivables timing and settlement patterns. For forecasting, we assume a steady +1% of revenue working-capital investment as a conservative base-case
A12: Projected Free Cash Flow to Firm (FCFF)
A13: Line item | B13: FY2025 | C13: FY2026 | D13: FY2027
A14: Revenue | B14: =INCOME_S!D4*(1+B5) -> 486882.75 | C14: =B14*(1+$C$5) -> 511226.89 | D14: =C14*(1+$D$5) -> 536788.24
A15: EBIT | B15: =B6*B14 -> 315976.74 | C15: =C14*C6 -> 326663.3 | D15: =D6*D14 -> 337628.59
A16: Tax on EBIT | B16: =-B15*INPUTS!B11 -> -118985.49 | C16: =-C15*INPUTS!B11 -> -123009.67 | D16: =-D15*INPUTS!B11 -> -127138.8
A17: NOPAT | B17: =B15+B16 -> 196991.24 | C17: =C15+C16 -> 203653.63 | D17: =D15+D16 -> 210489.79
A18: Capex | B18: =-B14*$B$8 -> -47288.22 | C18: =-C14*$C$8 -> -49652.631 | D18: =-D14*$D$8 -> -52135.263
A19: Change in NWC | B19: =-B14*$B$9 -> -4868.8275 | C19: =-C14*$C$9 -> -5112.2689 | D19: =-D14*$D$9 -> -5367.8824
A20: FCFF | B20: =(B17+B18+B19) -> 144834.2 | C20: =(C17+C18+C19) -> 148888.73 | D20: =(D17+D18+D19) -> 152986.64

Sheet DCF
A1: DCF Valuation (FCFF)
A2: If this company generates FCFF in the future, what is that stream worth today?
A3: Inputs (linked from INPUTS)
A4: WACC | B4: =INPUTS!B12 -> 0.264758 | C4: WACC is discount rate (required return). It represents the riskiness of the business.
A5: Terminal growth (g) | B5: =INPUTS!B13 -> 0.04 | C5: Higher WACC ⇒ future cash flows are worth less today
A6: Net debt (Debt - Cash) | B6: =INPUTS!B15 -> -259000.53 | C6: Lower WACC ⇒ worth more today
A7: Shares outstanding (mn) | B7: =INPUTS!B14 -> 4300.9284
A9: Present value of projected FCFF
A10: Year | B10: FCFF | C10: Discount factor | D10: PV of FCFF | E10: PV(FCFF)=FCFF​×Discount factort
A11: FY2025 | B11: =FORECAST!B20 -> 144834.2 | C11: =1/(1+$B$4)^1 -> 0.79066509 | D11: =(B11*C11) -> 114515.34
A12: FY2026 | B12: =FORECAST!C20 -> 148888.73 | C12: =1/(1+$B$4)^2 -> 0.62515129 | D12: =(B12*C12) -> 93077.984
A13: FY2027 | B13: =FORECAST!D20 -> 152986.64 | C13: =1/(1+$B$4)^3 -> 0.4942853 | D13: =(B13*C13) -> 75619.048
A14: Terminal value (end FY2027) | B14: =B13*(1+B5)/(B4-B5) -> 707899.64 | C14: =C13 -> 0.4942853 | D14: =B14*C14 -> 349904.38
A16: Value summary
A17: Enterprise value (PV FCFF + PV TV) | B17: =SUM(D11:D13)+(D14) -> 633116.76
A18: Equity value | B18: =B17-B6 -> 892117.29
A19: Value per share | B19: =B18/B7 -> 207.42435 | C19: Equity Value=EV−Net Debt
A21: Sensitivity: Equity value per share (WACC vs g)
A22: g \ WACC | B22: 0.14 | C22: 0.16 | D22: 0.18 | E22: 0.2 | F22: 0.22
A23: 0.02 | B23: =IF(0.14-0.02<=0,"-",((FORECAST!B20/(1+0.14)^1 + FORECAST!C20/(1+0.14)^2 + FORECAST!D20/(1+0.14)^3 + (FORECAST!D20*(1+0.02)/(0.14-0.02))/(1+0.14)^3) - $B$6)/$B$7) -> 344.48343 | C23: =IF(0.16-0.02<=0,"-",((FORECAST!B20/(1+0.16)^1 + FORECAST!C20/(1+0.16)^2 + FORECAST!D20/(1+0.16)^3 + (FORECAST!D20*(1+0.02)/(0.16-0.02))/(1+0.16)^3) - $B$6)/$B$7) -> 303.7963 | D23: =IF(0.18-0.02<=0,"-",((FORECAST!B20/(1+0.18)^1 + FORECAST!C20/(1+0.18)^2 + FORECAST!D20/(1+0.18)^3 + (FORECAST!D20*(1+0.02)/(0.18-0.02))/(1+0.18)^3) - $B$6)/$B$7) -> 273.28398 | E23: =IF(0.2-0.02<=0,"-",((FORECAST!B20/(1+0.2)^1 + FORECAST!C20/(1+0.2)^2 + FORECAST!D20/(1+0.2)^3 + (FORECAST!D20*(1+0.02)/(0.2-0.02))/(1+0.2)^3) - $B$6)/$B$7) -> 249.5547 | F23: =IF(0.22-0.02<=0,"-",((FORECAST!B20/(1+0.22)^1 + FORECAST!C20/(1+0.22)^2 + FORECAST!D20/(1+0.22)^3 + (FORECAST!D20*(1+0.02)/(0.22-0.02))/(1+0.22)^3) - $B$6)/$B$7) -> 230.5734
A24: 0.03 | B24: =IF(0.14-0.03<=0,"-",((FORECAST!B20/(1+0.14)^1 + FORECAST!C20/(1+0.14)^2 + FORECAST!D20/(1+0.14)^3 + (FORECAST!D20*(1+0.03)/(0.14-0.03))/(1+0.14)^3) - $B$6)/$B$7) -> 365.2186 | C24: =IF(0.16-0.03<=0,"-",((FORECAST!B20/(1+0.16)^1 + FORECAST!C20/(1+0.16)^2 + FORECAST!D20/(1+0.16)^3 + (FORECAST!D20*(1+0.03)/(0.16-0.03))/(1+0.16)^3) - $B$6)/$B$7) -> 318.3209 | D24: =IF(0.18-0.03<=0,"-",((FORECAST!B20/(1+0.18)^1 + FORECAST!C20/(1+0.18)^2 + FORECAST!D20/(1+0.18)^3 + (FORECAST!D20*(1+0.03)/(0.18-0.03))/(1+0.18)^3) - $B$6)/$B$7) -> 283.92826 | E24: =IF(0.2-0.03<=0,"-",((FORECAST!B20/(1+0.2)^1 + FORECAST!C20/(1+0.2)^2 + FORECAST!D20/(1+0.2)^3 + (FORECAST!D20*(1+0.03)/(0.2-0.03))/(1+0.2)^3) - $B$6)/$B$7) -> 257.62718 | F24: =IF(0.22-0.03<=0,"-",((FORECAST!B20/(1+0.22)^1 + FORECAST!C20/(1+0.22)^2 + FORECAST!D20/(1+0.22)^3 + (FORECAST!D20*(1+0.03)/(0.22-0.03))/(1+0.22)^3) - $B$6)/$B$7) -> 236.86249
A25: 0.04 | B25: =IF(0.14-0.04<=0,"-",((FORECAST!B20/(1+0.14)^1 + FORECAST!C20/(1+0.14)^2 + FORECAST!D20/(1+0.14)^3 + (FORECAST!D20*(1+0.04)/(0.14-0.04))/(1+0.14)^3) - $B$6)/$B$7) -> 390.10081 | C25: =IF(0.16-0.04<=0,"-",((FORECAST!B20/(1+0.16)^1 + FORECAST!C20/(1+0.16)^2 + FORECAST!D20/(1+0.16)^3 + (FORECAST!D20*(1+0.04)/(0.16-0.04))/(1+0.16)^3) - $B$6)/$B$7) -> 335.26625 | D25: =IF(0.18-0.04<=0,"-",((FORECAST!B20/(1+0.18)^1 + FORECAST!C20/(1+0.18)^2 + FORECAST!D20/(1+0.18)^3 + (FORECAST!D20*(1+0.04)/(0.18-0.04))/(1+0.18)^3) - $B$6)/$B$7) -> 296.09314 | E25: =IF(0.2-0.04<=0,"-",((FORECAST!B20/(1+0.2)^1 + FORECAST!C20/(1+0.2)^2 + FORECAST!D20/(1+0.2)^3 + (FORECAST!D20*(1+0.04)/(0.2-0.04))/(1+0.2)^3) - $B$6)/$B$7) -> 266.70873 | F25: =IF(0.22-0.04<=0,"-",((FORECAST!B20/(1+0.22)^1 + FORECAST!C20/(1+0.22)^2 + FORECAST!D20/(1+0.22)^3 + (FORECAST!D20*(1+0.04)/(0.22-0.04))/(1+0.22)^3) - $B$6)/$B$7) -> 243.85038
A26: 0.05 | B26: =IF(0.14-0.05<=0,"-",((FORECAST!B20/(1+0.14)^1 + FORECAST!C20/(1+0.14)^2 + FORECAST!D20/(1+0.14)^3 + (FORECAST!D20*(1+0.05)/(0.14-0.05))/(1+0.14)^3) - $B$6)/$B$7) -> 420.51239 | C26: =IF(0.16-0.05<=0,"-",((FORECAST!B20/(1+0.16)^1 + FORECAST!C20/(1+0.16)^2 + FORECAST!D20/(1+0.16)^3 + (FORECAST!D20*(1+0.05)/(0.16-0.05))/(1+0.16)^3) - $B$6)/$B$7) -> 355.29258 | D26: =IF(0.18-0.05<=0,"-",((FORECAST!B20/(1+0.18)^1 + FORECAST!C20/(1+0.18)^2 + FORECAST!D20/(1+0.18)^3 + (FORECAST!D20*(1+0.05)/(0.18-0.05))/(1+0.18)^3) - $B$6)/$B$7) -> 310.12955 | E26: =IF(0.2-0.05<=0,"-",((FORECAST!B20/(1+0.2)^1 + FORECAST!C20/(1+0.2)^2 + FORECAST!D20/(1+0.2)^3 + (FORECAST!D20*(1+0.05)/(0.2-0.05))/(1+0.2)^3) - $B$6)/$B$7) -> 277.00115 | F26: =IF(0.22-0.05<=0,"-",((FORECAST!B20/(1+0.22)^1 + FORECAST!C20/(1+0.22)^2 + FORECAST!D20/(1+0.22)^3 + (FORECAST!D20*(1+0.05)/(0.22-0.05))/(1+0.22)^3) - $B$6)/$B$7) -> 251.66036
A27: 0.06 | B27: =IF(0.14-0.06<=0,"-",((FORECAST!B20/(1+0.14)^1 + FORECAST!C20/(1+0.14)^2 + FORECAST!D20/(1+0.14)^3 + (FORECAST!D20*(1+0.06)/(0.14-0.06))/(1+0.14)^3) - $B$6)/$B$7) -> 458.52688 | C27: =IF(0.16-0.06<=0,"-",((FORECAST!B20/(1+0.16)^1 + FORECAST!C20/(1+0.16)^2 + FORECAST!D20/(1+0.16)^3 + (FORECAST!D20*(1+0.06)/(0.16-0.06))/(1+0.16)^3) - $B$6)/$B$7) -> 379.32418 | D27: =IF(0.18-0.06<=0,"-",((FORECAST!B20/(1+0.18)^1 + FORECAST!C20/(1+0.18)^2 + FORECAST!D20/(1+0.18)^3 + (FORECAST!D20*(1+0.06)/(0.18-0.06))/(1+0.18)^3) - $B$6)/$B$7) -> 326.50535 | E27: =IF(0.2-0.06<=0,"-",((FORECAST!B20/(1+0.2)^1 + FORECAST!C20/(1+0.2)^2 + FORECAST!D20/(1+0.2)^3 + (FORECAST!D20*(1+0.06)/(0.2-0.06))/(1+0.2)^3) - $B$6)/$B$7) -> 288.76392 | F27: =IF(0.22-0.06<=0,"-",((FORECAST!B20/(1+0.22)^1 + FORECAST!C20/(1+0.22)^2 + FORECAST!D20/(1+0.22)^3 + (FORECAST!D20*(1+0.06)/(0.22-0.06))/(1+0.22)^3) - $B$6)/$B$7) -> 260.44659
A29: =B19 -> 207.42435 | B29: 0.14 | C29: 0.16 | D29: 0.18 | E29: 0.2 | F29: 0.22
A30: 0.02 | B30: 344.48343 | C30: 303.7963 | D30: 273.28398 | E30: 249.5547 | F30: 230.5734
A31: 0.03 | B31: 365.2186 | C31: 318.3209 | D31: 283.92826 | E31: 257.62718 | F31: 236.86249
A32: 0.04 | B32: 390.10081 | C32: 335.26625 | D32: 296.09314 | E32: 266.70873 | F32: 243.85038
A33: 0.05 | B33: 420.51239 | C33: 355.29258 | D33: 310.12955 | E33: 277.00115 | F33: 251.66036
A34: 0.06 | B34: 458.52688 | C34: 379.32418 | D34: 326.50535 | E34: 288.76392 | F34: 260.44659

Sheet DASHBOARD
A1: OGDCL Financial Analysis & DCF Valuation Dashboard
A4: FY2024 Snapshot KPIs
A5: Revenue (PKR mn) | C5: EBIT margin | E5: Net margin | G5: ROE
A6: =INCOME_S!D4 -> 463697.86 | C6: =RATIOS!D5 -> 0.64897911 | E6: =RATIOS!D6 -> 0.45067228 | G6: =RATIOS!D8 -> 0.16711428
A8: Debt/Equity | C8: Cash conversion (CFO/NI) | E8: Closing cash (PKR mn) | G8: DCF value/share (PKR)
A9: =RATIOS!D10 -> 0.28289404 | C9: =RATIOS!D12 -> 0.50132089 | E9: =CF_S!D10 -> 258613.24 | G9: =DCF!B19 -> 207.42435
A11: Historical Trends (FY2022–FY2024)
A12: Year | B12: Revenue (PKR mn) | C12: Net profit (PKR mn) | D12: EBIT margin | E12: CFO (PKR mn)
A13: FY2022 | B13: =INCOME_S!B4 -> 335463.72 | C13: =INCOME_S!B12 -> 133783.75 | D13: =RATIOS!B5 -> 0.70011014 | E13: =CF_S!B4 -> 72364.346
A14: FY2023 | B14: =INCOME_S!C4 -> 413594.01 | C14: =INCOME_S!C12 -> 224617.8 | D14: =RATIOS!C5 -> 0.93929774 | E14: =CF_S!C4 -> 27817.162
A15: FY2024 | B15: =INCOME_S!D4 -> 463697.86 | C15: =INCOME_S!D12 -> 208975.77 | D15: =RATIOS!D5 -> 0.64897911 | E15: =CF_S!D4 -> 104763.92
A18: Forecast FCFF (FY2025–FY2027) & DCF Summary
A19: Year | B19: Revenue (PKR mn) | C19: FCFF (PKR mn) | D19: PV of FCFF (PKR mn) | F19: DCF Outputs
A20: FY2025 | B20: =FORECAST!B14 -> 486882.75 | C20: =FORECAST!B20 -> 144834.2 | D20: =DCF!D11 -> 114515.34 | F20: WACC | G20: =INPUTS!B12 -> 0.264758
A21: FY2026 | B21: =FORECAST!C14 -> 511226.89 | C21: =FORECAST!C20 -> 148888.73 | D21: =DCF!D12 -> 93077.984 | F21: g | G21: =INPUTS!B13 -> 0.04
A22: FY2027 | B22: =FORECAST!D14 -> 536788.24 | C22: =FORECAST!D20 -> 152986.64 | D22: =DCF!D13 -> 75619.048 | F22: EV (PKR mn) | G22: =DCF!B17 -> 633116.76
F23: Equity value (PKR mn) | G23: =DCF!B18 -> 892117.29
F24: Value/share (PKR) | G24: =DCF!B19 -> 207.42435
